Postile-0.1.1.dist-info/METADATA
Postile-0.1.1.dist-info/RECORD
Postile-0.1.1.dist-info/WHEEL
Postile-0.1.1.dist-info/entry_points.txt
Postile-0.1.1.dist-info/top_level.txt
postile/__init__.py
postile/postile.py
postile/sql.py
